trace_viewer/__init__.py
trace_viewer/cli.py
trace_viewer/listener.py
trace_viewer/capture/__init__.py
trace_viewer/capture/console.py
trace_viewer/capture/dom.py
trace_viewer/capture/network.py
trace_viewer/capture/screenshot.py
trace_viewer/capture/variables.py
trace_viewer/integrations/__init__.py
trace_viewer/integrations/reportportal.py
trace_viewer/stats/__init__.py
trace_viewer/stats/dashboard.py
trace_viewer/storage/__init__.py
trace_viewer/storage/trace_writer.py
trace_viewer/viewer/__init__.py
trace_viewer/viewer/comparator.py
trace_viewer/viewer/generator.py
trace_viewer/viewer/templates/.gitkeep
trace_viewer/viewer/templates/viewer.html
robotframework_trace_viewer-0.2.0.dist-info/METADATA
robotframework_trace_viewer-0.2.0.dist-info/WHEEL
robotframework_trace_viewer-0.2.0.dist-info/entry_points.txt
robotframework_trace_viewer-0.2.0.dist-info/licenses/LICENSE
robotframework_trace_viewer-0.2.0.dist-info/RECORD
