Metadata-Version: 2.4
Name: robotframework-trace-viewer
Version: 0.2.0
Summary: Visual trace viewer for Robot Framework test debugging
Project-URL: Homepage, https://github.com/thearchit3ct/robotframework-trace-viewer
Project-URL: Documentation, https://github.com/thearchit3ct/robotframework-trace-viewer#readme
Project-URL: Repository, https://github.com/thearchit3ct/robotframework-trace-viewer
Project-URL: Issues, https://github.com/thearchit3ct/robotframework-trace-viewer/issues
Author: Robot Framework Trace Viewer Contributors
License-Expression: MIT
License-File: LICENSE
Keywords: debugging,robotframework,selenium,testing,trace,viewer
Classifier: Development Status :: 3 - Alpha
Classifier: Framework :: Robot Framework
Classifier: Framework :: Robot Framework :: Tool
Classifier: Intended Audience :: Developers
Classifier: License :: OSI Approved :: MIT License
Classifier: Operating System :: OS Independent
Classifier: Programming Language :: Python :: 3
Classifier: Programming Language :: Python :: 3.9
Classifier: Programming Language :: Python :: 3.10
Classifier: Programming Language :: Python :: 3.11
Classifier: Programming Language :: Python :: 3.12
Classifier: Topic :: Software Development :: Quality Assurance
Classifier: Topic :: Software Development :: Testing
Requires-Python: >=3.9
Requires-Dist: click>=8.0
Requires-Dist: robotframework>=6.0
Requires-Dist: selenium>=4.0
Provides-Extra: dev
Requires-Dist: black>=23.0; extra == 'dev'
Requires-Dist: mypy>=1.0; extra == 'dev'
Requires-Dist: pytest-mock>=3.0; extra == 'dev'
Requires-Dist: pytest>=7.0; extra == 'dev'
Requires-Dist: ruff>=0.1.0; extra == 'dev'
